{
  "hosting": {
    "amplifyhosting": {
      "service": "amplifyhosting",
      "type": "cicd",
      "lastPushTimeStamp": "2021-10-05T15:01:31.528Z"
    }
  },
  "auth": {
    "cognito75c13d3c": {
      "service": "Cognito",
      "serviceType": "managed",
      "providerPlugin": "awscloudformation",
      "frontendAuthConfig": {
        "loginMechanisms": [
          "PREFERRED_USERNAME"
        ],
        "signupAttributes": [],
        "passwordProtectionSettings": {
          "passwordPolicyCharacters": []
        },
        "mfaTypes": [],
        "verificationMechanisms": []
      }
    }
  },
  "analytics": {
    "amplifyreactapp": {
      "service": "Pinpoint",
      "providerPlugin": "awscloudformation"
    }
  }
}